microsoft_MiniLM_L12_H384_uncased/__init__.py
microsoft_MiniLM_L12_H384_uncased/text_classification_model.py
microsoft_MiniLM_L12_H384_uncased-0.1.5.dist-info/LICENSE
microsoft_MiniLM_L12_H384_uncased-0.1.5.dist-info/METADATA
microsoft_MiniLM_L12_H384_uncased-0.1.5.dist-info/WHEEL
microsoft_MiniLM_L12_H384_uncased-0.1.5.dist-info/top_level.txt
microsoft_MiniLM_L12_H384_uncased-0.1.5.dist-info/RECORD
