Metadata-Version: 2.1
Name: microsoft-MiniLM-L12-H384-uncased
Version: 0.1.5
Summary: A library that leverages the pre-trained microsoft_MiniLM-L12-H384-uncased model for efficient and lightweight text classification tasks, with a focus on English. The library offers easy-to-use fine-tuning capabilities, making it suitable for rapid deployment in resource-constrained environments.
Home-page: https://github.com/mehrdadalmasi2020/microsoft_MiniLM_L12_H384_uncased
Author: Mehrdad ALMASI, Demival VASQUES FILHO
Author-email: mehrdad.al.2023@gmail.com, demival.vasques@uni.lu
Classifier: Programming Language :: Python :: 3
Classifier: License :: OSI Approved :: MIT License
Classifier: Operating System :: OS Independent
Requires-Python: >=3.6
License-File: LICENSE
Requires-Dist: transformers (<5.0.0,>=4.20.0)
Requires-Dist: tokenizers (<0.14.0,>=0.10.0)
Requires-Dist: torch (<2.0.0,>=1.7.0)
Requires-Dist: pandas (>=1.1.0)
Requires-Dist: scikit-learn (>=1.0)
Requires-Dist: numpy (<1.24.0,>=1.19.0)
